by_square/__init__.py
by_square/encode.py
by_square/serialize.py
by_square/types.py
by_square-0.3.dist-info/WHEEL
by_square-0.3.dist-info/METADATA
by_square-0.3.dist-info/RECORD
