Metadata-Version: 2.4
Name: by-square
Version: 0.3
Summary: Encoder and decoder of "by square" QR codes (PAY by square, INVOICE by square)
Author: Adam Zahradník
Author-email: Adam Zahradník <adam@zahradnik.xyz>
License-Expression: MIT
Classifier: Development Status :: 4 - Beta
Classifier: Intended Audience :: Developers
Classifier: License :: OSI Approved :: MIT License
Classifier: Programming Language :: Python :: 3
Classifier: Topic :: Software Development :: Libraries :: Python Modules
Classifier: Topic :: Office/Business :: Financial
Requires-Python: >=3.12
Project-URL: Homepage, https://github.com/gardenerik/by-square
